geotoolsconnector/__init__.py
geotoolsconnector/geotoolspipe.py
geotoolsconnector/run.py
geotoolsconnector-1.0.2.dist-info/METADATA
geotoolsconnector-1.0.2.dist-info/WHEEL
geotoolsconnector-1.0.2.dist-info/top_level.txt
geotoolsconnector-1.0.2.dist-info/RECORD
