Metadata-Version: 2.1
Name: geotoolsconnector
Version: 1.0.2
Summary: Fast and reliable way to analize geospatial data.
Author: Sanil Safić
Author-email: <safic.sanil@gmail.com>
Keywords: python,GeoTools,Geospatial analysis,Web Service,Geospatial data,Pipe request,GeoPandas,QGIS,PostGIS
Classifier: Development Status :: 3 - Alpha
Classifier: Intended Audience :: Developers
Classifier: Programming Language :: Python :: 3
Classifier: Operating System :: Unix
Classifier: Operating System :: MacOS :: MacOS X
Classifier: Operating System :: Microsoft :: Windows
Requires-Dist: flask
Requires-Dist: requests
Requires-Dist: asyncio
